README.md
setup.py
ApplyEnv.egg-info/PKG-INFO
ApplyEnv.egg-info/SOURCES.txt
ApplyEnv.egg-info/dependency_links.txt
ApplyEnv.egg-info/top_level.txt
applyenv/__init__.py
applyenv/applyenv.py