Metadata-Version: 2.1
Name: ApplyEnv
Version: 1.0.57
Summary: Populate variables in a tree-like schema
Home-page: https://github.com/
Author: ApplyEnv
Author-email: applyenv@protonmail.ch
License: UNKNOWN
Platform: UNKNOWN
Classifier: Operating System :: OS Independent
Classifier: License :: OSI Approved :: MIT License
Classifier: Programming Language :: Python :: 3
